aio_geojson_planefinderlocal/__init__.py
aio_geojson_planefinderlocal/__version__.py
aio_geojson_planefinderlocal/consts.py
aio_geojson_planefinderlocal/feed.py
aio_geojson_planefinderlocal/feed_entry.py
aio_geojson_planefinderlocal/feed_manager.py
aio_geojson_planefinderlocal-0.2.1.dist-info/LICENSE
aio_geojson_planefinderlocal-0.2.1.dist-info/METADATA
aio_geojson_planefinderlocal-0.2.1.dist-info/WHEEL
aio_geojson_planefinderlocal-0.2.1.dist-info/top_level.txt
aio_geojson_planefinderlocal-0.2.1.dist-info/RECORD
