Metadata-Version: 2.1
Name: aio-geojson-planefinderlocal
Version: 0.2.1
Summary: An async GeoJSON client library for planes using information from a Planefinder local server.
Home-page: https://github.com/kuchel77/python-aio-geojson-planefinderlocal
Author: Mark Kuchel
Author-email: mark@kuchel.net
Classifier: Programming Language :: Python :: 3.6
Classifier: Programming Language :: Python :: 3.7
Classifier: Programming Language :: Python :: 3.8
Classifier: License :: OSI Approved :: Apache Software License
Classifier: Operating System :: OS Independent
License-File: LICENSE
Requires-Dist: aio-geojson-client (>=0.11)
Requires-Dist: aiohttp (>=3.5.4)
Requires-Dist: pytz (>=2019.01)
